sphinx_nekochan/__init__.py
sphinx_nekochan/_static/sphinx_nekochan.css
sphinx_nekochan/data/nekochan_emoji.json
sphinx_nekochan-0.4.0.dist-info/licenses/LICENSE
sphinx_nekochan-0.4.0.dist-info/WHEEL
sphinx_nekochan-0.4.0.dist-info/METADATA
sphinx_nekochan-0.4.0.dist-info/RECORD
