Metadata-Version: 2.4
Name: sphinx-nekochan
Version: 0.4.0
Summary: A Sphinx extension for adding the Nekochan(cat) emoji to documents.
Keywords: sphinx,extension
Author-email: Takanori Suzuki <takanori@takanory.net>
Requires-Python: >=3.10
Classifier: Development Status :: 4 - Beta
Classifier: Framework :: Sphinx :: Extension
Classifier: Intended Audience :: Developers
Classifier: License :: OSI Approved :: MIT License
Classifier: Programming Language :: Python :: 3.10
Classifier: Programming Language :: Python :: 3.11
Classifier: Programming Language :: Python :: 3.12
Classifier: Programming Language :: Python :: 3.13
Classifier: Programming Language :: Python :: Implementation :: CPython
Classifier: Topic :: Software Development :: Libraries :: Python Modules
Classifier: Topic :: Text Processing :: Markup
Classifier: Topic :: Text Processing :: Markup :: Markdown
Classifier: Topic :: Text Processing :: Markup :: reStructuredText
License-File: LICENSE
Requires-Dist: sphinx>=8.0
Requires-Dist: ruff>=0.8.6 ; extra == "dev"
Requires-Dist: furo>=2024.8.6  ; extra == "docs"
Requires-Dist: matplotlib>=3.10.0 ; extra == "docs"
Requires-Dist: myst-parser>=4.0.0 ; extra == "docs"
Requires-Dist: sphinx>=8.1.3 ; extra == "docs"
Requires-Dist: sphinx-copybutton>=0.5.2 ; extra == "docs"
Requires-Dist: sphinx-design>=0.6.1 ; extra == "docs"
Requires-Dist: sphinx-revealjs==3.1.1 ; extra == "docs"
Requires-Dist: sphinxext-opengraph>=0.9.1 ; extra == "docs"
Project-URL: Documentation, https://sphinx-nekochan.readthedocs.io/
Project-URL: Repository, https://github.com/takanory/sphinx-nekochan
Provides-Extra: dev
Provides-Extra: docs
